ingot.py
ingotdr-0.0.5.dist-info/LICENSE
ingotdr-0.0.5.dist-info/METADATA
ingotdr-0.0.5.dist-info/WHEEL
ingotdr-0.0.5.dist-info/top_level.txt
ingotdr-0.0.5.dist-info/RECORD
