Metadata-Version: 2.1
Name: ingotdr
Version: 0.0.5
Summary: INGOT-DR (INterpretable GrOup Testing for Drug Resistance)
Home-page: https://github.com/hoomanzabeti/ingotdr
Author: Hooman Zabeti
Author-email: hzabeti@sfu.ca
License: UNKNOWN
Platform: UNKNOWN
Requires-Dist: numpy
Requires-Dist: pandas
Requires-Dist: pulp
Requires-Dist: sklearn
